newrange.py
pyvivc.py
pyvivc-1.0.dist-info/LICENSE.txt
pyvivc-1.0.dist-info/METADATA
pyvivc-1.0.dist-info/WHEEL
pyvivc-1.0.dist-info/top_level.txt
pyvivc-1.0.dist-info/RECORD
