Metadata-Version: 2.1
Name: pyvivc
Version: 1.0
Summary: numerical deconvolution and convolution methods working for inequal and incompatible timepoints between impulse and response curves for application in IVIVC level A
Home-page: https://github.com/scheckley/pyvivc
Author: Stephen Checkley
Author-email: scheckley@gmail.com
Project-URL: Bug Reports, https://github.com/scheckley/pyvivc
Classifier: Programming Language :: Python :: 3
Classifier: License :: OSI Approved :: GNU General Public License v3 (GPLv3)
Classifier: Operating System :: OS Independent
Requires-Python: >=3.9
License-File: LICENSE.txt
Requires-Dist: scipy
Requires-Dist: pandas
Requires-Dist: numpy
